dragonmapper/__init__.py
dragonmapper/hanzi.py
dragonmapper/transcriptions.py
dragonmapper/data/__init__.py
dragonmapper/data/hanzi_pinyin_characters.tsv
dragonmapper/data/hanzi_pinyin_words.tsv
dragonmapper/data/transcriptions.csv
dragonmapper-0.3.0.dist-info/METADATA
dragonmapper-0.3.0.dist-info/WHEEL
dragonmapper-0.3.0.dist-info/licenses/AUTHORS.rst
dragonmapper-0.3.0.dist-info/licenses/LICENSE.txt
dragonmapper-0.3.0.dist-info/RECORD
