Metadata-Version: 2.3
Name: dragonmapper
Version: 0.3.0
Summary: Identification and conversion functions for Chinese text processing
Project-URL: Documentation, https://tsroten.github.io/dragonmapper
Project-URL: Source code, https://github.com/tsroten/dragonmapper
Author: Thomas Roten
License: MIT
Keywords: bopomofo,characters,chinese,convert,hanzi,ipa,mandarin,pinyin,readings,transcription,zhuyin
Classifier: Development Status :: 5 - Production/Stable
Classifier: Intended Audience :: Developers
Classifier: License :: OSI Approved :: MIT License
Classifier: Operating System :: OS Independent
Classifier: Programming Language :: Python
Classifier: Programming Language :: Python :: 3
Classifier: Programming Language :: Python :: 3.9
Classifier: Programming Language :: Python :: 3.10
Classifier: Programming Language :: Python :: 3.11
Classifier: Programming Language :: Python :: 3.12
Classifier: Programming Language :: Python :: 3.13
Classifier: Topic :: Software Development :: Libraries :: Python Modules
Classifier: Topic :: Text Processing :: Linguistic
Requires-Python: >=3.9
Requires-Dist: hanzidentifier~=1.2
Requires-Dist: zhon~=2.0
